key_lib_test/__init__.py
key_lib_test/main.py
key_lib_test-0.1.dist-info/METADATA
key_lib_test-0.1.dist-info/WHEEL
key_lib_test-0.1.dist-info/top_level.txt
key_lib_test-0.1.dist-info/RECORD
