Metadata-Version: 2.1
Name: key_lib_test
Version: 0.1
Summary: Uma biblioteca de exemplo
Home-page: https://github.com/FelipeLacerdaAmorim/PyLibTest
Author: Felipe Lacerda
Author-email: joaofelipe.amorim@aluno.uece.br
Classifier: Programming Language :: Python :: 3
Classifier: License :: OSI Approved :: MIT License
Classifier: Operating System :: OS Independent
Requires-Python: >=3.12
Requires-Dist: fastapi-keycloak
Requires-Dist: Pyjwt
Requires-Dist: requests
Requires-Dist: starlette
